{
    "data": {
        "total_vehiculos": 216773,
        "total_paginas": 3613,
        "pagina_actual": 1,
        "tamaño_pagina": 60,
        "vehiculos": [
            {
                "census_tract_2020": "",
                "base_msrp": "",
                "cafv_type": "",
                "city": "",
                "county": "",
                "dol_vehicle_id": "",
                "electric_range": "",
                "electric_utility": "",
                "ev_type": "",
                "geocoded_column": "",
                "legislative_district": "",
                "make": "",
                "model": "",
                "model_year": "",
                "state": "",
                "vin": "",
                "zip_code": ""
            },
            {
                "census_tract_2020": "53033020100",
                "base_msrp": "0",
                "cafv_type": "Clean Alternative Fuel Vehicle Eligible",
                "city": "Shoreline",
                "county": "King",
                "dol_vehicle_id": "125450447",
                "electric_range": "75",
                "electric_utility": "CITY OF SEATTLE - (WA)|CITY OF TACOMA - (WA)",
                "ev_type": "Battery Electric Vehicle (BEV)",
                "geocoded_column": "POINT (-122.36498 47.72238)",
                "legislative_district": "32",
                "make": "NISSAN",
                "model": "LEAF",
                "model_year": "2013",
                "state": "WA",
                "vin": "1N4AZ0CP8D",
                "zip_code": "98177"
            },
            {
                "census_tract_2020": "53033006300",
                "base_msrp": "0",
                "cafv_type": "Clean Alternative Fuel Vehicle Eligible",
                "city": "Seattle",
                "county": "King",
                "dol_vehicle_id": "101662900",
                "electric_range": "270",
                "electric_utility": "CITY OF SEATTLE - (WA)|CITY OF TACOMA - (WA)",
                "ev_type": "Battery Electric Vehicle (BEV)",
                "geocoded_column": "POINT (-122.30207 47.64085)",
                "legislative_district": "43",
                "make": "TESLA",
                "model": "MODEL S",
                "model_year": "2019",
                "state": "WA",
                "vin": "5YJSA1E45K",
                "zip_code": "98112"
            },
            {
                "census_tract_2020": "53035092803",
                "base_msrp": "0",
                "cafv_type": "Eligibility unknown as battery range has not been researched",
                "city": "Olalla",
                "county": "Kitsap",
                "dol_vehicle_id": "272118717",
                "electric_range": "0",
                "electric_utility": "PUGET SOUND ENERGY INC",
                "ev_type": "Battery Electric Vehicle (BEV)",
                "geocoded_column": "POINT (-122.54729 47.42602)",
                "legislative_district": "26",
                "make": "VOLKSWAGEN",
                "model": "ID.4",
                "model_year": "2021",
                "state": "WA",
                "vin": "WVGUNPE28M",
                "zip_code": "98359"
            },
            {
                "census_tract_2020": "53067010400",
                "base_msrp": "0",
                "cafv_type": "Not eligible due to low battery range",
                "city": "Olympia",
                "county": "Thurston",
                "dol_vehicle_id": "349372929",
                "electric_range": "25",
                "electric_utility": "PUGET SOUND ENERGY INC",
                "ev_type": "Plug-in Hybrid Electric Vehicle (PHEV)",
                "geocoded_column": "POINT (-122.89166 47.03956)",
                "legislative_district": "22",
                "make": "TOYOTA",
                "model": "PRIUS PRIME",
                "model_year": "2017",
                "state": "WA",
                "vin": "JTDKARFP6H",
                "zip_code": "98501"
            },
            {
                "census_tract_2020": "53067010300",
                "base_msrp": "0",
                "cafv_type": "Not eligible due to low battery range",
                "city": "Olympia",
                "county": "Thurston",
                "dol_vehicle_id": "171625653",
                "electric_range": "19",
                "electric_utility": "PUGET SOUND ENERGY INC",
                "ev_type": "Plug-in Hybrid Electric Vehicle (PHEV)",
                "geocoded_column": "POINT (-122.87741 47.05997)",
                "legislative_district": "22",
                "make": "FORD",
                "model": "C-MAX",
                "model_year": "2016",
                "state": "WA",
                "vin": "1FADP5CU9G",
                "zip_code": "98506"
            },
            {
                "census_tract_2020": "53061052009",
                "base_msrp": "0",
                "cafv_type": "Clean Alternative Fuel Vehicle Eligible",
                "city": "Bothell",
                "county": "Snohomish",
                "dol_vehicle_id": "127104078",
                "electric_range": "266",
                "electric_utility": "PUGET SOUND ENERGY INC",
                "ev_type": "Battery Electric Vehicle (BEV)",
                "geocoded_column": "POINT (-122.21061 47.83448)",
                "legislative_district": "1",
                "make": "TESLA",
                "model": "MODEL 3",
                "model_year": "2020",
                "state": "WA",
                "vin": "5YJ3E1EA9L",
                "zip_code": "98012"
            },
            {
                "census_tract_2020": "53061052009",
                "base_msrp": "0",
                "cafv_type": "Clean Alternative Fuel Vehicle Eligible",
                "city": "Bothell",
                "county": "Snohomish",
                "dol_vehicle_id": "104605490",
                "electric_range": "249",
                "electric_utility": "PUGET SOUND ENERGY INC",
                "ev_type": "Battery Electric Vehicle (BEV)",
                "geocoded_column": "POINT (-122.21061 47.83448)",
                "legislative_district": "1",
                "make": "TESLA",
                "model": "MODEL S",
                "model_year": "2018",
                "state": "WA",
                "vin": "5YJSA1E26J",
                "zip_code": "98012"
            },
            {
                "census_tract_2020": "53035090201",
                "base_msrp": "0",
                "cafv_type": "Not eligible due to low battery range",
                "city": "Poulsbo",
                "county": "Kitsap",
                "dol_vehicle_id": "240675865",
                "electric_range": "21",
                "electric_utility": "PUGET SOUND ENERGY INC",
                "ev_type": "Plug-in Hybrid Electric Vehicle (PHEV)",
                "geocoded_column": "POINT (-122.64681 47.73689)",
                "legislative_district": "23",
                "make": "JEEP",
                "model": "WRANGLER",
                "model_year": "2023",
                "state": "WA",
                "vin": "1C4JJXP6XP",
                "zip_code": "98370"
            },
            {
                "census_tract_2020": "53067012730",
                "base_msrp": "0",
                "cafv_type": "Not eligible due to low battery range",
                "city": "Rochester",
                "county": "Thurston",
                "dol_vehicle_id": "152190328",
                "electric_range": "17",
                "electric_utility": "PUGET SOUND ENERGY INC",
                "ev_type": "Plug-in Hybrid Electric Vehicle (PHEV)",
                "geocoded_column": "POINT (-123.08743 46.82175)",
                "legislative_district": "20",
                "make": "BMW",
                "model": "X3",
                "model_year": "2021",
                "state": "WA",
                "vin": "5UXTS1C01M",
                "zip_code": "98579"
            },
            {
                "census_tract_2020": "53033027100",
                "base_msrp": "0",
                "cafv_type": "Clean Alternative Fuel Vehicle Eligible",
                "city": "Burien",
                "county": "King",
                "dol_vehicle_id": "213452795",
                "electric_range": "73",
                "electric_utility": "CITY OF SEATTLE - (WA)|CITY OF TACOMA - (WA)",
                "ev_type": "Battery Electric Vehicle (BEV)",
                "geocoded_column": "POINT (-122.3317 47.50314)",
                "legislative_district": "33",
                "make": "NISSAN",
                "model": "LEAF",
                "model_year": "2012",
                "state": "WA",
                "vin": "JN1AZ0CP2C",
                "zip_code": "98168"
            },
            {
                "census_tract_2020": "53035090902",
                "base_msrp": "0",
                "cafv_type": "Clean Alternative Fuel Vehicle Eligible",
                "city": "Bainbridge Island",
                "county": "Kitsap",
                "dol_vehicle_id": "104355884",
                "electric_range": "322",
                "electric_utility": "PUGET SOUND ENERGY INC",
                "ev_type": "Battery Electric Vehicle (BEV)",
                "geocoded_column": "POINT (-122.521 47.62728)",
                "legislative_district": "23",
                "make": "TESLA",
                "model": "MODEL 3",
                "model_year": "2020",
                "state": "WA",
                "vin": "5YJ3E1EBXL",
                "zip_code": "98110"
            },
            {
                "census_tract_2020": "53033000900",
                "base_msrp": "0",
                "cafv_type": "Clean Alternative Fuel Vehicle Eligible",
                "city": "Seattle",
                "county": "King",
                "dol_vehicle_id": "231656428",
                "electric_range": "75",
                "electric_utility": "CITY OF SEATTLE - (WA)|CITY OF TACOMA - (WA)",
                "ev_type": "Battery Electric Vehicle (BEV)",
                "geocoded_column": "POINT (-122.30253 47.72656)",
                "legislative_district": "46",
                "make": "NISSAN",
                "model": "LEAF",
                "model_year": "2013",
                "state": "WA",
                "vin": "1N4AZ0CP8D",
                "zip_code": "98125"
            },
            {
                "census_tract_2020": "53061052008",
                "base_msrp": "0",
                "cafv_type": "Not eligible due to low battery range",
                "city": "Mill Creek",
                "county": "Snohomish",
                "dol_vehicle_id": "272548881",
                "electric_range": "17",
                "electric_utility": "PUGET SOUND ENERGY INC",
                "ev_type": "Plug-in Hybrid Electric Vehicle (PHEV)",
                "geocoded_column": "POINT (-122.21061 47.83448)",
                "legislative_district": "44",
                "make": "BMW",
                "model": "X3",
                "model_year": "2021",
                "state": "WA",
                "vin": "5UXTS1C04M",
                "zip_code": "98012"
            },
            {
                "census_tract_2020": "53035091302",
                "base_msrp": "0",
                "cafv_type": "Clean Alternative Fuel Vehicle Eligible",
                "city": "Silverdale",
                "county": "Kitsap",
                "dol_vehicle_id": "151753045",
                "electric_range": "239",
                "electric_utility": "PUGET SOUND ENERGY INC",
                "ev_type": "Battery Electric Vehicle (BEV)",
                "geocoded_column": "POINT (-122.69275 47.65171)",
                "legislative_district": "23",
                "make": "KIA",
                "model": "NIRO",
                "model_year": "2020",
                "state": "WA",
                "vin": "KNDCE3LG3L",
                "zip_code": "98383"
            },
            {
                "census_tract_2020": "53061052203",
                "base_msrp": "0",
                "cafv_type": "Clean Alternative Fuel Vehicle Eligible",
                "city": "Monroe",
                "county": "Snohomish",
                "dol_vehicle_id": "254596093",
                "electric_range": "33",
                "electric_utility": "PUGET SOUND ENERGY INC",
                "ev_type": "Plug-in Hybrid Electric Vehicle (PHEV)",
                "geocoded_column": "POINT (-121.98087 47.8526)",
                "legislative_district": "39",
                "make": "KIA",
                "model": "NIRO",
                "model_year": "2023",
                "state": "WA",
                "vin": "KNDCR3LF8P",
                "zip_code": "98272"
            },
            {
                "census_tract_2020": "53061052010",
                "base_msrp": "0",
                "cafv_type": "Clean Alternative Fuel Vehicle Eligible",
                "city": "Bothell",
                "county": "Snohomish",
                "dol_vehicle_id": "273626384",
                "electric_range": "238",
                "electric_utility": "PUGET SOUND ENERGY INC",
                "ev_type": "Battery Electric Vehicle (BEV)",
                "geocoded_column": "POINT (-122.21061 47.83448)",
                "legislative_district": "1",
                "make": "TESLA",
                "model": "MODEL X",
                "model_year": "2018",
                "state": "WA",
                "vin": "5YJXCAE20J",
                "zip_code": "98012"
            },
            {
                "census_tract_2020": "53035080102",
                "base_msrp": "0",
                "cafv_type": "Eligibility unknown as battery range has not been researched",
                "city": "Bremerton",
                "county": "Kitsap",
                "dol_vehicle_id": "230680012",
                "electric_range": "0",
                "electric_utility": "PUGET SOUND ENERGY INC",
                "ev_type": "Battery Electric Vehicle (BEV)",
                "geocoded_column": "POINT (-122.61136 47.5752)",
                "legislative_district": "23",
                "make": "TESLA",
                "model": "MODEL 3",
                "model_year": "2023",
                "state": "WA",
                "vin": "5YJ3E1EA3P",
                "zip_code": "98310"
            },
            {
                "census_tract_2020": "53061041605",
                "base_msrp": "0",
                "cafv_type": "Clean Alternative Fuel Vehicle Eligible",
                "city": "Everett",
                "county": "Snohomish",
                "dol_vehicle_id": "107329708",
                "electric_range": "125",
                "electric_utility": "PUGET SOUND ENERGY INC",
                "ev_type": "Battery Electric Vehicle (BEV)",
                "geocoded_column": "POINT (-122.18637 47.89251)",
                "legislative_district": "44",
                "make": "VOLKSWAGEN",
                "model": "E-GOLF",
                "model_year": "2019",
                "state": "WA",
                "vin": "WVWKR7AU8K",
                "zip_code": "98208"
            },
            {
                "census_tract_2020": "53061041609",
                "base_msrp": "0",
                "cafv_type": "Not eligible due to low battery range",
                "city": "Mill Creek",
                "county": "Snohomish",
                "dol_vehicle_id": "349890761",
                "electric_range": "19",
                "electric_utility": "PUGET SOUND ENERGY INC",
                "ev_type": "Plug-in Hybrid Electric Vehicle (PHEV)",
                "geocoded_column": "POINT (-122.21061 47.83448)",
                "legislative_district": "44",
                "make": "FORD",
                "model": "FUSION",
                "model_year": "2015",
                "state": "WA",
                "vin": "3FA6P0SU6F",
                "zip_code": "98012"
            },
            {
                "census_tract_2020": "53033008003",
                "base_msrp": "0",
                "cafv_type": "Clean Alternative Fuel Vehicle Eligible",
                "city": "Seattle",
                "county": "King",
                "dol_vehicle_id": "187481402",
                "electric_range": "249",
                "electric_utility": "CITY OF SEATTLE - (WA)|CITY OF TACOMA - (WA)",
                "ev_type": "Battery Electric Vehicle (BEV)",
                "geocoded_column": "POINT (-122.34468 47.61578)",
                "legislative_district": "36",
                "make": "TESLA",
                "model": "MODEL S",
                "model_year": "2018",
                "state": "WA",
                "vin": "5YJSA1E25J",
                "zip_code": "98121"
            },
            {
                "census_tract_2020": "53061051933",
                "base_msrp": "0",
                "cafv_type": "Clean Alternative Fuel Vehicle Eligible",
                "city": "Bothell",
                "county": "Snohomish",
                "dol_vehicle_id": "171277795",
                "electric_range": "215",
                "electric_utility": "PUGET SOUND ENERGY INC",
                "ev_type": "Battery Electric Vehicle (BEV)",
                "geocoded_column": "POINT (-122.21061 47.83448)",
                "legislative_district": "1",
                "make": "TESLA",
                "model": "MODEL 3",
                "model_year": "2018",
                "state": "WA",
                "vin": "5YJ3E1EA8J",
                "zip_code": "98012"
            },
            {
                "census_tract_2020": "53061051934",
                "base_msrp": "0",
                "cafv_type": "Clean Alternative Fuel Vehicle Eligible",
                "city": "Bothell",
                "county": "Snohomish",
                "dol_vehicle_id": "225742457",
                "electric_range": "32",
                "electric_utility": "PUGET SOUND ENERGY INC",
                "ev_type": "Plug-in Hybrid Electric Vehicle (PHEV)",
                "geocoded_column": "POINT (-122.21061 47.83448)",
                "legislative_district": "1",
                "make": "CHRYSLER",
                "model": "PACIFICA",
                "model_year": "2022",
                "state": "WA",
                "vin": "2C4RC1S75N",
                "zip_code": "98012"
            },
            {
                "census_tract_2020": "53033002100",
                "base_msrp": "0",
                "cafv_type": "Clean Alternative Fuel Vehicle Eligible",
                "city": "Seattle",
                "county": "King",
                "dol_vehicle_id": "3832804",
                "electric_range": "84",
                "electric_utility": "CITY OF SEATTLE - (WA)|CITY OF TACOMA - (WA)",
                "ev_type": "Battery Electric Vehicle (BEV)",
                "geocoded_column": "POINT (-122.31676 47.68156)",
                "legislative_district": "46",
                "make": "NISSAN",
                "model": "LEAF",
                "model_year": "2016",
                "state": "WA",
                "vin": "1N4BZ0CP9G",
                "zip_code": "98115"
            },
            {
                "census_tract_2020": "53061052401",
                "base_msrp": "0",
                "cafv_type": "Clean Alternative Fuel Vehicle Eligible",
                "city": "Snohomish",
                "county": "Snohomish",
                "dol_vehicle_id": "115260113",
                "electric_range": "81",
                "electric_utility": "PUGET SOUND ENERGY INC",
                "ev_type": "Battery Electric Vehicle (BEV)",
                "geocoded_column": "POINT (-122.09305 47.91265)",
                "legislative_district": "44",
                "make": "BMW",
                "model": "I3",
                "model_year": "2017",
                "state": "WA",
                "vin": "WBY1Z6C34H",
                "zip_code": "98290"
            },
            {
                "census_tract_2020": "53061052203",
                "base_msrp": "0",
                "cafv_type": "Eligibility unknown as battery range has not been researched",
                "city": "Monroe",
                "county": "Snohomish",
                "dol_vehicle_id": "276163597",
                "electric_range": "0",
                "electric_utility": "PUGET SOUND ENERGY INC",
                "ev_type": "Battery Electric Vehicle (BEV)",
                "geocoded_column": "POINT (-121.98087 47.8526)",
                "legislative_district": "39",
                "make": "KIA",
                "model": "EV9",
                "model_year": "2024",
                "state": "WA",
                "vin": "KNDAFFS56R",
                "zip_code": "98272"
            },
            {
                "census_tract_2020": "53067010700",
                "base_msrp": "0",
                "cafv_type": "Clean Alternative Fuel Vehicle Eligible",
                "city": "Olympia",
                "county": "Thurston",
                "dol_vehicle_id": "259889416",
                "electric_range": "39",
                "electric_utility": "PUGET SOUND ENERGY INC",
                "ev_type": "Plug-in Hybrid Electric Vehicle (PHEV)",
                "geocoded_column": "POINT (-122.89166 47.03956)",
                "legislative_district": "22",
                "make": "BMW",
                "model": "X5",
                "model_year": "2024",
                "state": "WA",
                "vin": "5UX43EU03R",
                "zip_code": "98501"
            },
            {
                "census_tract_2020": "53061052007",
                "base_msrp": "0",
                "cafv_type": "Clean Alternative Fuel Vehicle Eligible",
                "city": "Bothell",
                "county": "Snohomish",
                "dol_vehicle_id": "283945000",
                "electric_range": "47",
                "electric_utility": "PUGET SOUND ENERGY INC",
                "ev_type": "Plug-in Hybrid Electric Vehicle (PHEV)",
                "geocoded_column": "POINT (-122.21061 47.83448)",
                "legislative_district": "44",
                "make": "HONDA",
                "model": "CLARITY",
                "model_year": "2018",
                "state": "WA",
                "vin": "JHMZC5F39J",
                "zip_code": "98012"
            },
            {
                "census_tract_2020": "53067012002",
                "base_msrp": "0",
                "cafv_type": "Clean Alternative Fuel Vehicle Eligible",
                "city": "Olympia",
                "county": "Thurston",
                "dol_vehicle_id": "172700223",
                "electric_range": "38",
                "electric_utility": "PUGET SOUND ENERGY INC",
                "ev_type": "Plug-in Hybrid Electric Vehicle (PHEV)",
                "geocoded_column": "POINT (-122.92333 47.03779)",
                "legislative_district": "22",
                "make": "CHEVROLET",
                "model": "VOLT",
                "model_year": "2014",
                "state": "WA",
                "vin": "1G1RF6E48E",
                "zip_code": "98502"
            },
            {
                "census_tract_2020": "53061041606",
                "base_msrp": "0",
                "cafv_type": "Clean Alternative Fuel Vehicle Eligible",
                "city": "Everett",
                "county": "Snohomish",
                "dol_vehicle_id": "112339580",
                "electric_range": "291",
                "electric_utility": "PUGET SOUND ENERGY INC",
                "ev_type": "Battery Electric Vehicle (BEV)",
                "geocoded_column": "POINT (-122.18637 47.89251)",
                "legislative_district": "44",
                "make": "TESLA",
                "model": "MODEL Y",
                "model_year": "2020",
                "state": "WA",
                "vin": "5YJYGDEE6L",
                "zip_code": "98208"
            },
            {
                "census_tract_2020": "53035092600",
                "base_msrp": "0",
                "cafv_type": "Not eligible due to low battery range",
                "city": "Port Orchard",
                "county": "Kitsap",
                "dol_vehicle_id": "475641512",
                "electric_range": "16",
                "electric_utility": "PUGET SOUND ENERGY INC",
                "ev_type": "Plug-in Hybrid Electric Vehicle (PHEV)",
                "geocoded_column": "POINT (-122.63847 47.54103)",
                "legislative_district": "26",
                "make": "AUDI",
                "model": "A3",
                "model_year": "2018",
                "state": "WA",
                "vin": "WAUTPBFF9J",
                "zip_code": "98366"
            },
            {
                "census_tract_2020": "53077003200",
                "base_msrp": "0",
                "cafv_type": "Not eligible due to low battery range",
                "city": "Selah",
                "county": "Yakima",
                "dol_vehicle_id": "253964189",
                "electric_range": "25",
                "electric_utility": "PACIFICORP",
                "ev_type": "Plug-in Hybrid Electric Vehicle (PHEV)",
                "geocoded_column": "POINT (-120.53145 46.65405)",
                "legislative_district": "15",
                "make": "JEEP",
                "model": "GRAND CHEROKEE",
                "model_year": "2022",
                "state": "WA",
                "vin": "1C4RJYC66N",
                "zip_code": "98942"
            },
            {
                "census_tract_2020": "53033023604",
                "base_msrp": "0",
                "cafv_type": "Clean Alternative Fuel Vehicle Eligible",
                "city": "Bellevue",
                "county": "King",
                "dol_vehicle_id": "145566893",
                "electric_range": "75",
                "electric_utility": "PUGET SOUND ENERGY INC||CITY OF TACOMA - (WA)",
                "ev_type": "Battery Electric Vehicle (BEV)",
                "geocoded_column": "POINT (-122.12053 47.61334)",
                "legislative_district": "41",
                "make": "NISSAN",
                "model": "LEAF",
                "model_year": "2013",
                "state": "WA",
                "vin": "1N4AZ0CP2D",
                "zip_code": "98007"
            },
            {
                "census_tract_2020": "53067012331",
                "base_msrp": "0",
                "cafv_type": "Clean Alternative Fuel Vehicle Eligible",
                "city": "Olympia",
                "county": "Thurston",
                "dol_vehicle_id": "104932131",
                "electric_range": "266",
                "electric_utility": "PUGET SOUND ENERGY INC",
                "ev_type": "Battery Electric Vehicle (BEV)",
                "geocoded_column": "POINT (-122.81754 46.98876)",
                "legislative_district": "2",
                "make": "TESLA",
                "model": "MODEL 3",
                "model_year": "2020",
                "state": "WA",
                "vin": "5YJ3E1EA1L",
                "zip_code": "98513"
            },
            {
                "census_tract_2020": "53035080101",
                "base_msrp": "0",
                "cafv_type": "Clean Alternative Fuel Vehicle Eligible",
                "city": "Bremerton",
                "county": "Kitsap",
                "dol_vehicle_id": "127147555",
                "electric_range": "291",
                "electric_utility": "PUGET SOUND ENERGY INC",
                "ev_type": "Battery Electric Vehicle (BEV)",
                "geocoded_column": "POINT (-122.61136 47.5752)",
                "legislative_district": "23",
                "make": "TESLA",
                "model": "MODEL Y",
                "model_year": "2020",
                "state": "WA",
                "vin": "5YJYGDEF2L",
                "zip_code": "98310"
            },
            {
                "census_tract_2020": "53035091100",
                "base_msrp": "0",
                "cafv_type": "Eligibility unknown as battery range has not been researched",
                "city": "Poulsbo",
                "county": "Kitsap",
                "dol_vehicle_id": "236667742",
                "electric_range": "0",
                "electric_utility": "PUGET SOUND ENERGY INC",
                "ev_type": "Battery Electric Vehicle (BEV)",
                "geocoded_column": "POINT (-122.64681 47.73689)",
                "legislative_district": "23",
                "make": "AUDI",
                "model": "Q4",
                "model_year": "2023",
                "state": "WA",
                "vin": "WA1L2BFZ9P",
                "zip_code": "98370"
            },
            {
                "census_tract_2020": "53033009400",
                "base_msrp": "0",
                "cafv_type": "Clean Alternative Fuel Vehicle Eligible",
                "city": "Seattle",
                "county": "King",
                "dol_vehicle_id": "180748151",
                "electric_range": "114",
                "electric_utility": "CITY OF SEATTLE - (WA)|CITY OF TACOMA - (WA)",
                "ev_type": "Battery Electric Vehicle (BEV)",
                "geocoded_column": "POINT (-122.30866 47.57874)",
                "legislative_district": "37",
                "make": "BMW",
                "model": "I3",
                "model_year": "2018",
                "state": "WA",
                "vin": "WBY7Z2C5XJ",
                "zip_code": "98144"
            },
            {
                "census_tract_2020": "53061052120",
                "base_msrp": "0",
                "cafv_type": "Clean Alternative Fuel Vehicle Eligible",
                "city": "Everett",
                "county": "Snohomish",
                "dol_vehicle_id": "115796502",
                "electric_range": "84",
                "electric_utility": "PUGET SOUND ENERGY INC",
                "ev_type": "Battery Electric Vehicle (BEV)",
                "geocoded_column": "POINT (-122.18637 47.89251)",
                "legislative_district": "44",
                "make": "NISSAN",
                "model": "LEAF",
                "model_year": "2016",
                "state": "WA",
                "vin": "1N4BZ0CP3G",
                "zip_code": "98208"
            },
            {
                "census_tract_2020": "53025010401",
                "base_msrp": "0",
                "cafv_type": "Not eligible due to low battery range",
                "city": "Ephrata",
                "county": "Grant",
                "dol_vehicle_id": "233856479",
                "electric_range": "25",
                "electric_utility": "PUD NO 2 OF GRANT COUNTY",
                "ev_type": "Plug-in Hybrid Electric Vehicle (PHEV)",
                "geocoded_column": "POINT (-119.55096 47.31909)",
                "legislative_district": "13",
                "make": "JEEP",
                "model": "GRAND CHEROKEE",
                "model_year": "2022",
                "state": "WA",
                "vin": "1C4RJYB67N",
                "zip_code": "98823"
            },
            {
                "census_tract_2020": "53077001702",
                "base_msrp": "0",
                "cafv_type": "Eligibility unknown as battery range has not been researched",
                "city": "Yakima",
                "county": "Yakima",
                "dol_vehicle_id": "269268261",
                "electric_range": "0",
                "electric_utility": "PACIFICORP",
                "ev_type": "Battery Electric Vehicle (BEV)",
                "geocoded_column": "POINT (-120.50723 46.60452)",
                "legislative_district": "15",
                "make": "CHEVROLET",
                "model": "BLAZER EV",
                "model_year": "2024",
                "state": "WA",
                "vin": "3GNKDBRJXR",
                "zip_code": "98901"
            },
            {
                "census_tract_2020": "53035081100",
                "base_msrp": "0",
                "cafv_type": "Clean Alternative Fuel Vehicle Eligible",
                "city": "Bremerton",
                "county": "Kitsap",
                "dol_vehicle_id": "251044041",
                "electric_range": "53",
                "electric_utility": "PUGET SOUND ENERGY INC",
                "ev_type": "Plug-in Hybrid Electric Vehicle (PHEV)",
                "geocoded_column": "POINT (-122.6563 47.56739)",
                "legislative_district": "26",
                "make": "CHEVROLET",
                "model": "VOLT",
                "model_year": "2016",
                "state": "WA",
                "vin": "1G1RC6S5XG",
                "zip_code": "98312"
            },
            {
                "census_tract_2020": "53033027300",
                "base_msrp": "0",
                "cafv_type": "Clean Alternative Fuel Vehicle Eligible",
                "city": "Seatac",
                "county": "King",
                "dol_vehicle_id": "8116965",
                "electric_range": "125",
                "electric_utility": "CITY OF SEATTLE - (WA)|CITY OF TACOMA - (WA)",
                "ev_type": "Battery Electric Vehicle (BEV)",
                "geocoded_column": "POINT (-122.3317 47.50314)",
                "legislative_district": "33",
                "make": "VOLKSWAGEN",
                "model": "E-GOLF",
                "model_year": "2019",
                "state": "WA",
                "vin": "WVWPR7AU2K",
                "zip_code": "98168"
            },
            {
                "census_tract_2020": "53033003202",
                "base_msrp": "0",
                "cafv_type": "Clean Alternative Fuel Vehicle Eligible",
                "city": "Seattle",
                "county": "King",
                "dol_vehicle_id": "167141285",
                "electric_range": "81",
                "electric_utility": "CITY OF SEATTLE - (WA)|CITY OF TACOMA - (WA)",
                "ev_type": "Battery Electric Vehicle (BEV)",
                "geocoded_column": "POINT (-122.38418 47.70044)",
                "legislative_district": "36",
                "make": "BMW",
                "model": "I3",
                "model_year": "2015",
                "state": "WA",
                "vin": "WBY1Z2C59F",
                "zip_code": "98117"
            },
            {
                "census_tract_2020": "53061041609",
                "base_msrp": "0",
                "cafv_type": "Clean Alternative Fuel Vehicle Eligible",
                "city": "Everett",
                "county": "Snohomish",
                "dol_vehicle_id": "203569915",
                "electric_range": "215",
                "electric_utility": "PUGET SOUND ENERGY INC",
                "ev_type": "Battery Electric Vehicle (BEV)",
                "geocoded_column": "POINT (-122.18637 47.89251)",
                "legislative_district": "44",
                "make": "TESLA",
                "model": "MODEL 3",
                "model_year": "2018",
                "state": "WA",
                "vin": "5YJ3E1EB9J",
                "zip_code": "98208"
            },
            {
                "census_tract_2020": "53033032221",
                "base_msrp": "0",
                "cafv_type": "Clean Alternative Fuel Vehicle Eligible",
                "city": "Issaquah",
                "county": "King",
                "dol_vehicle_id": "240946065",
                "electric_range": "107",
                "electric_utility": "PUGET SOUND ENERGY INC||CITY OF TACOMA - (WA)",
                "ev_type": "Battery Electric Vehicle (BEV)",
                "geocoded_column": "POINT (-122.00292 47.54748)",
                "legislative_district": "5",
                "make": "NISSAN",
                "model": "LEAF",
                "model_year": "2017",
                "state": "WA",
                "vin": "1N4BZ0CP4H",
                "zip_code": "98029"
            },
            {
                "census_tract_2020": "53067010910",
                "base_msrp": "0",
                "cafv_type": "Clean Alternative Fuel Vehicle Eligible",
                "city": "Tumwater",
                "county": "Thurston",
                "dol_vehicle_id": "121108942",
                "electric_range": "215",
                "electric_utility": "PUGET SOUND ENERGY INC",
                "ev_type": "Battery Electric Vehicle (BEV)",
                "geocoded_column": "POINT (-122.9131 47.01359)",
                "legislative_district": "22",
                "make": "TESLA",
                "model": "MODEL 3",
                "model_year": "2018",
                "state": "WA",
                "vin": "5YJ3E1EA0J",
                "zip_code": "98512"
            },
            {
                "census_tract_2020": "53033024301",
                "base_msrp": "0",
                "cafv_type": "Clean Alternative Fuel Vehicle Eligible",
                "city": "Mercer Island",
                "county": "King",
                "dol_vehicle_id": "109213814",
                "electric_range": "81",
                "electric_utility": "PUGET SOUND ENERGY INC||CITY OF TACOMA - (WA)",
                "ev_type": "Battery Electric Vehicle (BEV)",
                "geocoded_column": "POINT (-122.21238 47.57816)",
                "legislative_district": "41",
                "make": "BMW",
                "model": "I3",
                "model_year": "2017",
                "state": "WA",
                "vin": "WBY1Z6C5XH",
                "zip_code": "98040"
            },
            {
                "census_tract_2020": "53033003202",
                "base_msrp": "0",
                "cafv_type": "Clean Alternative Fuel Vehicle Eligible",
                "city": "Seattle",
                "county": "King",
                "dol_vehicle_id": "303209672",
                "electric_range": "215",
                "electric_utility": "CITY OF SEATTLE - (WA)|CITY OF TACOMA - (WA)",
                "ev_type": "Battery Electric Vehicle (BEV)",
                "geocoded_column": "POINT (-122.38591 47.67597)",
                "legislative_district": "36",
                "make": "TESLA",
                "model": "MODEL 3",
                "model_year": "2018",
                "state": "WA",
                "vin": "5YJ3E1EB7J",
                "zip_code": "98107"
            },
            {
                "census_tract_2020": "53035092102",
                "base_msrp": "0",
                "cafv_type": "Clean Alternative Fuel Vehicle Eligible",
                "city": "Port Orchard",
                "county": "Kitsap",
                "dol_vehicle_id": "100517840",
                "electric_range": "107",
                "electric_utility": "PUGET SOUND ENERGY INC",
                "ev_type": "Battery Electric Vehicle (BEV)",
                "geocoded_column": "POINT (-122.68516 47.50645)",
                "legislative_district": "35",
                "make": "NISSAN",
                "model": "LEAF",
                "model_year": "2017",
                "state": "WA",
                "vin": "1N4BZ0CP4H",
                "zip_code": "98367"
            },
            {
                "census_tract_2020": "53067011627",
                "base_msrp": "0",
                "cafv_type": "Clean Alternative Fuel Vehicle Eligible",
                "city": "Lacey",
                "county": "Thurston",
                "dol_vehicle_id": "217036361",
                "electric_range": "238",
                "electric_utility": "PUGET SOUND ENERGY INC",
                "ev_type": "Battery Electric Vehicle (BEV)",
                "geocoded_column": "POINT (-122.82324 47.04437)",
                "legislative_district": "2",
                "make": "CHEVROLET",
                "model": "BOLT EV",
                "model_year": "2018",
                "state": "WA",
                "vin": "1G1FX6S05J",
                "zip_code": "98503"
            },
            {
                "census_tract_2020": "53067011721",
                "base_msrp": "0",
                "cafv_type": "Clean Alternative Fuel Vehicle Eligible",
                "city": "Olympia",
                "county": "Thurston",
                "dol_vehicle_id": "177568856",
                "electric_range": "220",
                "electric_utility": "PUGET SOUND ENERGY INC",
                "ev_type": "Battery Electric Vehicle (BEV)",
                "geocoded_column": "POINT (-122.89166 47.03956)",
                "legislative_district": "22",
                "make": "TESLA",
                "model": "MODEL 3",
                "model_year": "2019",
                "state": "WA",
                "vin": "5YJ3E1EB5K",
                "zip_code": "98501"
            },
            {
                "census_tract_2020": "53033010001",
                "base_msrp": "0",
                "cafv_type": "Clean Alternative Fuel Vehicle Eligible",
                "city": "Seattle",
                "county": "King",
                "dol_vehicle_id": "127485886",
                "electric_range": "291",
                "electric_utility": "CITY OF SEATTLE - (WA)|CITY OF TACOMA - (WA)",
                "ev_type": "Battery Electric Vehicle (BEV)",
                "geocoded_column": "POINT (-122.30346 47.55379)",
                "legislative_district": "37",
                "make": "TESLA",
                "model": "MODEL Y",
                "model_year": "2020",
                "state": "WA",
                "vin": "5YJYGDEE0L",
                "zip_code": "98108"
            },
            {
                "census_tract_2020": "53035090102",
                "base_msrp": "0",
                "cafv_type": "Clean Alternative Fuel Vehicle Eligible",
                "city": "Kingston",
                "county": "Kitsap",
                "dol_vehicle_id": "124737140",
                "electric_range": "238",
                "electric_utility": "PUGET SOUND ENERGY INC",
                "ev_type": "Battery Electric Vehicle (BEV)",
                "geocoded_column": "POINT (-122.4977 47.79802)",
                "legislative_district": "23",
                "make": "CHEVROLET",
                "model": "BOLT EV",
                "model_year": "2019",
                "state": "WA",
                "vin": "1G1FY6S0XK",
                "zip_code": "98346"
            },
            {
                "census_tract_2020": "53029970500",
                "base_msrp": "44100",
                "cafv_type": "Not eligible due to low battery range",
                "city": "Oak Harbor",
                "county": "Island",
                "dol_vehicle_id": "89813",
                "electric_range": "14",
                "electric_utility": "PUGET SOUND ENERGY INC",
                "ev_type": "Plug-in Hybrid Electric Vehicle (PHEV)",
                "geocoded_column": "POINT (-122.64682 48.29077)",
                "legislative_district": "10",
                "make": "BMW",
                "model": "330E",
                "model_year": "2017",
                "state": "WA",
                "vin": "WBA8E1C36H",
                "zip_code": "98277"
            },
            {
                "census_tract_2020": "53077001602",
                "base_msrp": "0",
                "cafv_type": "Clean Alternative Fuel Vehicle Eligible",
                "city": "Yakima",
                "county": "Yakima",
                "dol_vehicle_id": "156242754",
                "electric_range": "220",
                "electric_utility": "PACIFICORP",
                "ev_type": "Battery Electric Vehicle (BEV)",
                "geocoded_column": "POINT (-120.50723 46.60452)",
                "legislative_district": "15",
                "make": "TESLA",
                "model": "MODEL 3",
                "model_year": "2019",
                "state": "WA",
                "vin": "5YJ3E1EB8K",
                "zip_code": "98901"
            },
            {
                "census_tract_2020": "53033010501",
                "base_msrp": "0",
                "cafv_type": "Clean Alternative Fuel Vehicle Eligible",
                "city": "Seattle",
                "county": "King",
                "dol_vehicle_id": "337290635",
                "electric_range": "215",
                "electric_utility": "CITY OF SEATTLE - (WA)|CITY OF TACOMA - (WA)",
                "ev_type": "Battery Electric Vehicle (BEV)",
                "geocoded_column": "POINT (-122.38415 47.53755)",
                "legislative_district": "34",
                "make": "TESLA",
                "model": "MODEL 3",
                "model_year": "2018",
                "state": "WA",
                "vin": "5YJ3E1EA2J",
                "zip_code": "98136"
            },
            {
                "census_tract_2020": "53067012211",
                "base_msrp": "0",
                "cafv_type": "Clean Alternative Fuel Vehicle Eligible",
                "city": "Olympia",
                "county": "Thurston",
                "dol_vehicle_id": "103640638",
                "electric_range": "35",
                "electric_utility": "PUGET SOUND ENERGY INC",
                "ev_type": "Plug-in Hybrid Electric Vehicle (PHEV)",
                "geocoded_column": "POINT (-122.87741 47.05997)",
                "legislative_district": "22",
                "make": "CHEVROLET",
                "model": "VOLT",
                "model_year": "2012",
                "state": "WA",
                "vin": "1G1RH6E44C",
                "zip_code": "98506"
            },
            {
                "census_tract_2020": "53067012100",
                "base_msrp": "0",
                "cafv_type": "Eligibility unknown as battery range has not been researched",
                "city": "Olympia",
                "county": "Thurston",
                "dol_vehicle_id": "259139044",
                "electric_range": "0",
                "electric_utility": "PUGET SOUND ENERGY INC",
                "ev_type": "Battery Electric Vehicle (BEV)",
                "geocoded_column": "POINT (-122.87741 47.05997)",
                "legislative_district": "22",
                "make": "TESLA",
                "model": "MODEL Y",
                "model_year": "2023",
                "state": "WA",
                "vin": "7SAYGAEE3P",
                "zip_code": "98506"
            },
            {
                "census_tract_2020": "53035091400",
                "base_msrp": "0",
                "cafv_type": "Clean Alternative Fuel Vehicle Eligible",
                "city": "Bremerton",
                "county": "Kitsap",
                "dol_vehicle_id": "6250954",
                "electric_range": "87",
                "electric_utility": "PUGET SOUND ENERGY INC",
                "ev_type": "Battery Electric Vehicle (BEV)",
                "geocoded_column": "POINT (-122.6563 47.56739)",
                "legislative_district": "35",
                "make": "FIAT",
                "model": "500",
                "model_year": "2015",
                "state": "WA",
                "vin": "3C3CFFGE5F",
                "zip_code": "98312"
            },
            {
                "census_tract_2020": "53067011410",
                "base_msrp": "0",
                "cafv_type": "Eligibility unknown as battery range has not been researched",
                "city": "Lacey",
                "county": "Thurston",
                "dol_vehicle_id": "257530010",
                "electric_range": "0",
                "electric_utility": "PUGET SOUND ENERGY INC",
                "ev_type": "Battery Electric Vehicle (BEV)",
                "geocoded_column": "POINT (-122.82324 47.04437)",
                "legislative_district": "22",
                "make": "KIA",
                "model": "EV6",
                "model_year": "2024",
                "state": "WA",
                "vin": "KNDC3DLC2R",
                "zip_code": "98503"
            }
        ]
    }
}